{
    "PermissionList":[
        {
            "PermissioGroupName":"用户设置",
            "PermissionGroupID":"0",
            "PermissionGroupList":[
                {
                    "PermissionID":"100",
                    "PermissionName":"获取所有用户"
                },
                {
                    "PermissionID":"101",
                    "PermissionName":"获取用户"
                },
                {
                    "PermissionID":"102",
                    "PermissionName":"添加用户"
                },
                {
                    "PermissionID":"103",
                    "PermissionName":"更新用户"
                },
                {
                    "PermissionID":"104",
                    "PermissionName":"删除用户"
                },
                {
                    "PermissionID":"105",
                    "PermissionName":"更新用户权限"
                }
            ]
        },
        {
            "PermissioGroupName":"基础设置",
            "PermissionGroupID":"1",
            "PermissionGroupList":[
                {
                    "PermissionID":"200",
                    "PermissionName":"同步台账站点列表"
                },
                {
                    "PermissionID":"201",
                    "PermissionName":"获取台账站点"
                },
                {
                    "PermissionID":"202",
                    "PermissionName":"同步台账站点"
                },
                {
                    "PermissionID":"203",
                    "PermissionName":"获取测试点列表"
                },
                {
                    "PermissionID":"204",
                    "PermissionName":"同步报告模板列表"
                },
                {
                    "PermissionID":"205",
                    "PermissionName":"获取报告模板"
                },
                {
                    "PermissionID":"206",
                    "PermissionName":"获取报告模板文件"
                },
                {
                    "PermissionID":"207",
                    "PermissionName":"同步报告模板"
                },
                {
                    "PermissionID":"208",
                    "PermissionName":"？？？？？"
                },
                {
                    "PermissionID":"209",
                    "PermissionName":"获取自定义属性"
                },
                {
                    "PermissionID":"210",
                    "PermissionName":"同步自定义属性"
                }
            ]
        },
        {
            "PermissioGroupName":"任务设置",
            "PermissionGroupID":"2",
            "PermissionGroupList":[
                {
                    "PermissionID":"300",
                    "PermissionName":"？？？"
                },
                {
                    "PermissionID":"301",
                    "PermissionName":"获取任务"
                },
                {
                    "PermissionID":"302",
                    "PermissionName":"同步任务"
                },
                {
                    "PermissionID":"303",
                    "PermissionName":"？？？"
                },
                {
                    "PermissionID":"304",
                    "PermissionName":"获取任务子项"
                },
                {
                    "PermissionID":"305",
                    "PermissionName":"获取任务子项图像文件"
                },
                {
                    "PermissionID":"306",
                    "PermissionName":"同步任务子项"
                },
                {
                    "PermissionID":"307",
                    "PermissionName":"同步任务数据"
                }
            ]
        }
    ]

}